pyreduce/__init__.py
pyreduce/__main__.py
pyreduce/cli.py
pyreduce/clipnflip.py
pyreduce/combine_frames.py
pyreduce/configuration.py
pyreduce/continuum_normalization.py
pyreduce/cwrappers.py
pyreduce/datasets.py
pyreduce/echelle.py
pyreduce/estimate_background_scatter.py
pyreduce/extract.py
pyreduce/extraction_height.py
pyreduce/pipeline.py
pyreduce/rectify.py
pyreduce/reduce.py
pyreduce/slit_curve.py
pyreduce/trace.py
pyreduce/util.py
pyreduce/wavelength_calibration.py
pyreduce/clib/__init__.py
pyreduce/clib/_slitfunc_2d.cpython-313-x86_64-linux-gnu.so
pyreduce/clib/_slitfunc_2d.cpython-314-x86_64-linux-gnu.so
pyreduce/clib/_slitfunc_bd.cpython-313-x86_64-linux-gnu.so
pyreduce/clib/_slitfunc_bd.cpython-314-x86_64-linux-gnu.so
pyreduce/clib/build_extract.py
pyreduce/clib/slit_func_2d_xi_zeta_bd.c
pyreduce/clib/slit_func_2d_xi_zeta_bd.h
pyreduce/clib/slit_func_bd.c
pyreduce/clib/slit_func_bd.h
pyreduce/instruments/__init__.py
pyreduce/instruments/common.py
pyreduce/instruments/filters.py
pyreduce/instruments/instrument_info.py
pyreduce/instruments/models.py
pyreduce/instruments/ANDES_YJH/__init__.py
pyreduce/instruments/ANDES_YJH/config.yaml
pyreduce/instruments/ANDES_YJH/order_centers_h.yaml
pyreduce/instruments/ANDES_YJH/order_centers_j.yaml
pyreduce/instruments/ANDES_YJH/order_centers_y.yaml
pyreduce/instruments/ANDES_YJH/settings.json
pyreduce/instruments/CRIRES_PLUS/__init__.py
pyreduce/instruments/CRIRES_PLUS/config.yaml
pyreduce/instruments/CRIRES_PLUS/mask_det1.fits.gz
pyreduce/instruments/CRIRES_PLUS/mask_det2.fits.gz
pyreduce/instruments/CRIRES_PLUS/mask_det3.fits.gz
pyreduce/instruments/CRIRES_PLUS/settings.json
pyreduce/instruments/CRIRES_PLUS/wavecal_J1228_det1.npz
pyreduce/instruments/CRIRES_PLUS/wavecal_J1228_det2.npz
pyreduce/instruments/CRIRES_PLUS/wavecal_J1228_det3.npz
pyreduce/instruments/HARPN/__init__.py
pyreduce/instruments/HARPN/config.yaml
pyreduce/instruments/HARPN/settings.json
pyreduce_astro-0.7.dist-info/METADATA
pyreduce_astro-0.7.dist-info/WHEEL
pyreduce_astro-0.7.dist-info/entry_points.txt
pyreduce_astro-0.7.dist-info/RECORD
pyreduce_astro-0.7.dist-info/licenses/LICENSE
