Metadata-Version: 2.4
Name: pyreduce-astro
Version: 0.7
Summary: A data reduction package for echelle spectrographs
Project-URL: Homepage, https://github.com/ivh/PyReduce
Project-URL: Documentation, https://pyreduce-astro.readthedocs.io
Project-URL: Repository, https://github.com/ivh/PyReduce
Project-URL: Issues, https://github.com/ivh/PyReduce/issues
Author: Nikolai Piskunov, Thomas Marquart, Ansgar Wehrhahn
Maintainer-email: Thomas Marquart <thomas.marquart@astro.uu.se>
License: GPL-3.0-or-later
License-File: LICENSE
Classifier: Development Status :: 4 - Beta
Classifier: Intended Audience :: Science/Research
Classifier: License :: OSI Approved :: GNU General Public License v3 or later (GPLv3+)
Classifier: Programming Language :: C
Classifier: Programming Language :: Python :: 3
Classifier: Programming Language :: Python :: 3.13
Classifier: Programming Language :: Python :: 3.14
Classifier: Topic :: Scientific/Engineering :: Astronomy
Requires-Python: >=3.13
Requires-Dist: astropy>=5.3.0
Requires-Dist: cffi>=1.17.1
Requires-Dist: click>=8.1.0
Requires-Dist: colorlog>=6.8.0
Requires-Dist: corner>=2.2.0
Requires-Dist: emcee>=3.1.0
Requires-Dist: joblib>=1.3.0
Requires-Dist: jsonschema>=4.20.0
Requires-Dist: matplotlib>=3.8.0
Requires-Dist: numpy>=1.26.0
Requires-Dist: pillow>=10.0.0
Requires-Dist: pydantic>=2.5.0
Requires-Dist: python-dateutil>=2.8.0
Requires-Dist: pyyaml>=6.0.0
Requires-Dist: scikit-image>=0.22.0
Requires-Dist: scipy>=1.11.0
Requires-Dist: spectres>=2.2.0
Requires-Dist: tqdm>=4.66.0
